examples/install-on-linode/app.py
examples/install-on-linode/make_stackscript.py
linode_api4/__init__.py
linode_api4/common.py
linode_api4/errors.py
linode_api4/linode_client.py
linode_api4/login_client.py
linode_api4/paginated_list.py
linode_api4/polling.py
linode_api4/util.py
linode_api4/version.py
linode_api4/groups/__init__.py
linode_api4/groups/account.py
linode_api4/groups/beta.py
linode_api4/groups/database.py
linode_api4/groups/domain.py
linode_api4/groups/group.py
linode_api4/groups/image.py
linode_api4/groups/linode.py
linode_api4/groups/lke.py
linode_api4/groups/lke_tier.py
linode_api4/groups/longview.py
linode_api4/groups/maintenance.py
linode_api4/groups/monitor.py
linode_api4/groups/monitor_api.py
linode_api4/groups/networking.py
linode_api4/groups/nodebalancer.py
linode_api4/groups/object_storage.py
linode_api4/groups/placement.py
linode_api4/groups/polling.py
linode_api4/groups/profile.py
linode_api4/groups/region.py
linode_api4/groups/support.py
linode_api4/groups/tag.py
linode_api4/groups/volume.py
linode_api4/groups/vpc.py
linode_api4/objects/__init__.py
linode_api4/objects/account.py
linode_api4/objects/base.py
linode_api4/objects/beta.py
linode_api4/objects/database.py
linode_api4/objects/dbase.py
linode_api4/objects/domain.py
linode_api4/objects/filtering.py
linode_api4/objects/image.py
linode_api4/objects/linode.py
linode_api4/objects/linode_interfaces.py
linode_api4/objects/lke.py
linode_api4/objects/longview.py
linode_api4/objects/monitor.py
linode_api4/objects/monitor_api.py
linode_api4/objects/networking.py
linode_api4/objects/nodebalancer.py
linode_api4/objects/object_storage.py
linode_api4/objects/placement.py
linode_api4/objects/profile.py
linode_api4/objects/region.py
linode_api4/objects/serializable.py
linode_api4/objects/support.py
linode_api4/objects/tag.py
linode_api4/objects/volume.py
linode_api4/objects/vpc.py
linode_api4-5.37.0.dist-info/licenses/LICENSE
linode_api4-5.37.0.dist-info/METADATA
linode_api4-5.37.0.dist-info/WHEEL
linode_api4-5.37.0.dist-info/top_level.txt
linode_api4-5.37.0.dist-info/RECORD
