Metadata-Version: 2.4
Name: linode_api4
Version: 5.37.0
Summary: The official Python SDK for Linode API v4
Author-email: Linode <devs@linode.com>
License: BSD-3-Clause
Project-URL: Homepage, https://github.com/linode/linode_api4-python
Project-URL: Documentation, https://linode-api4.readthedocs.io/
Project-URL: Repository, https://github.com/linode/linode_api4-python.git
Keywords: akamai,Akamai Connected Cloud,linode,cloud,SDK,Linode APIv4
Classifier: Development Status :: 5 - Production/Stable
Classifier: Intended Audience :: Developers
Classifier: Topic :: Software Development :: Libraries
Classifier: License :: OSI Approved :: BSD License
Classifier: Programming Language :: Python
Classifier: Programming Language :: Python :: 3
Classifier: Programming Language :: Python :: 3.9
Classifier: Programming Language :: Python :: 3.10
Classifier: Programming Language :: Python :: 3.11
Classifier: Programming Language :: Python :: 3.12
Requires-Python: >=3.9
License-File: LICENSE
Requires-Dist: requests
Requires-Dist: polling
Requires-Dist: deprecated
Provides-Extra: test
Requires-Dist: tox>=4.4.0; extra == "test"
Provides-Extra: dev
Requires-Dist: tox>=4.4.0; extra == "dev"
Requires-Dist: mock>=5.0.0; extra == "dev"
Requires-Dist: pytest>=7.3.1; extra == "dev"
Requires-Dist: httpretty>=1.1.4; extra == "dev"
Requires-Dist: black>=23.1.0; extra == "dev"
Requires-Dist: isort>=5.12.0; extra == "dev"
Requires-Dist: autoflake>=2.0.1; extra == "dev"
Requires-Dist: pylint; extra == "dev"
Requires-Dist: twine>=4.0.2; extra == "dev"
Requires-Dist: build>=0.10.0; extra == "dev"
Requires-Dist: Sphinx>=6.0.0; extra == "dev"
Requires-Dist: sphinx-autobuild>=2021.3.14; extra == "dev"
Requires-Dist: sphinxcontrib-fulltoc>=1.2.0; extra == "dev"
Requires-Dist: build>=0.10.0; extra == "dev"
Requires-Dist: twine>=4.0.2; extra == "dev"
Requires-Dist: pytest-rerunfailures; extra == "dev"
Provides-Extra: doc
Requires-Dist: Sphinx>=6.0.0; extra == "doc"
Requires-Dist: sphinx-autobuild>=2021.3.14; extra == "doc"
Requires-Dist: sphinxcontrib-fulltoc>=1.2.0; extra == "doc"
Dynamic: license-file
